SentryEve/SentryEve.py
SentryEve/__init__.py
sentry_eve-0.0.0.1rc3.dist-info/LICENSE
sentry_eve-0.0.0.1rc3.dist-info/METADATA
sentry_eve-0.0.0.1rc3.dist-info/WHEEL
sentry_eve-0.0.0.1rc3.dist-info/top_level.txt
sentry_eve-0.0.0.1rc3.dist-info/RECORD
