Metadata-Version: 2.1
Name: sentry-eve
Version: 0.0.0.1rc3
Summary: Eve Sentry support
Home-page: https://github.com/standart-ag/sentry-eve
Author: Standart AG, LLC
Author-email: it@standart.lv
License: UNKNOWN
Platform: UNKNOWN
Classifier: Programming Language :: Python :: 3
Classifier: License :: OSI Approved :: MIT License
Classifier: Operating System :: OS Independent
Requires-Dist: eve
Requires-Dist: raven[flask]
